[{"user":"adi","item":"1","id":1},{"user":"adi","item":"4","id":2},{"user":"adi","item":"7","id":3},{"user":"adi","item":"2","id":5},{"user":"adi","item":"3","id":6},{"user":"FG","item":"2","id":9},{"user":"FG","item":"7","id":10},{"user":"gb","item":"8","id":11},{"user":"gb","item":"10","id":12},{"user":"gb","item":"5","id":13},{"user":"gb","item":"9","id":14},{"user":"gb","item":"6","id":15},{"user":"Customer","item":"1","id":23},{"user":"Customer","item":"2","id":24},{"user":"Customer","item":"4","id":25},{"user":"Maddie","item":"1","id":26},{"user":"Customer","item":"7","id":27},{"user":"Customer","item":"8","id":28},{"user":"Adi","item":"1","id":29},{"user":"Adi","item":"3","id":30}]